BLASTn_Extract/__init__.py
BLASTn_Extract/blastn_extract.py
BLASTn_Extract-0.1.1.data/scripts/blastn_extract.py
BLASTn_Extract-0.1.1.dist-info/METADATA
BLASTn_Extract-0.1.1.dist-info/RECORD
BLASTn_Extract-0.1.1.dist-info/WHEEL
BLASTn_Extract-0.1.1.dist-info/top_level.txt
