Metadata-Version: 2.1
Name: BLASTn-Extract
Version: 0.1.1
Summary: Internal BFSSI package for querying BLASTn results and filtering contig FASTA files
Home-page: https://github.com/bfssi-forest-dussault/BLASTn_Extract
Author: Forest Dussault
Author-email: forest.dussault@canada.ca
License: UNKNOWN
Platform: UNKNOWN
Requires-Dist: click
